skinterpret/__init__.py
skinterpret/feature_extraction/__init__.py
skinterpret/feature_extraction/text.py
scikit_feature_interpreter-0.0.3.dist-info/LICENSE
scikit_feature_interpreter-0.0.3.dist-info/METADATA
scikit_feature_interpreter-0.0.3.dist-info/WHEEL
scikit_feature_interpreter-0.0.3.dist-info/top_level.txt
scikit_feature_interpreter-0.0.3.dist-info/RECORD
